pythonpp/__init__.py
pythonpp/pythonpp.py
pythonpp-2.2.dist-info/LICENSE
pythonpp-2.2.dist-info/METADATA
pythonpp-2.2.dist-info/WHEEL
pythonpp-2.2.dist-info/top_level.txt
pythonpp-2.2.dist-info/RECORD
