Metadata-Version: 2.1
Name: pythonpp
Version: 2.2
Summary: UNKNOWN
Home-page: https://github.com/KentoNishi/PythonPP
Author: Kento Nishi, Ronak Badhe
Author-email: kento24gs@outlook.com, ronak.badhe@gmail.com
License: UNKNOWN
Platform: UNKNOWN
Classifier: Programming Language :: Python :: 3
Classifier: License :: OSI Approved :: MIT License
Classifier: Operating System :: OS Independent
Requires-Python: >=3.0
